djangocms_installer/__init__.py
djangocms_installer/__main__.py
djangocms_installer/compat.py
djangocms_installer/main.py
djangocms_installer/utils.py
djangocms_installer/config/__init__.py
djangocms_installer/config/data.py
djangocms_installer/config/ini.py
djangocms_installer/config/internal.py
djangocms_installer/config/settings.py
djangocms_installer/config/urls_i18n.py
djangocms_installer/config/urls_noi18n.py
djangocms_installer/django/__init__.py
djangocms_installer/install/__init__.py
djangocms_installer/share/__init__.py
djangocms_installer/share/create_user.py
djangocms_installer/share/starting_page.json
djangocms_installer/share/starting_page.py
djangocms_installer/share/test_image.jpg
djangocms_installer/share/test_image.png
djangocms_installer/share/templates/basic/base.html
djangocms_installer/share/templates/basic/fullwidth.html
djangocms_installer/share/templates/basic/sidebar_left.html
djangocms_installer/share/templates/basic/sidebar_right.html
djangocms_installer/share/templates/bootstrap/base.html
djangocms_installer/share/templates/bootstrap/feature.html
djangocms_installer/share/templates/bootstrap/menu.html
djangocms_installer/share/templates/bootstrap/page.html
tests/__init__.py
tests/base.py
tests/config.py
tests/django.py
tests/main.py
djangocms_installer-2.0.0.dist-info/LICENSE
djangocms_installer-2.0.0.dist-info/METADATA
djangocms_installer-2.0.0.dist-info/WHEEL
djangocms_installer-2.0.0.dist-info/entry_points.txt
djangocms_installer-2.0.0.dist-info/top_level.txt
djangocms_installer-2.0.0.dist-info/RECORD
