Metadata-Version: 2.1
Name: djangocms-installer
Version: 2.0.0
Summary: Command to easily bootstrap django CMS projects
Home-page: https://github.com/nephila/djangocms-installer
Author: Iacopo Spalletti
Author-email: i.spalletti@nephila.it
License: BSD
Project-URL: Documentation, https://djangocms-installer.readthedocs.io/
Platform: UNKNOWN
Classifier: Development Status :: 5 - Production/Stable
Classifier: Framework :: Django
Classifier: Intended Audience :: Developers
Classifier: License :: OSI Approved :: BSD License
Classifier: Natural Language :: English
Classifier: Programming Language :: Python :: 3
Classifier: Programming Language :: Python :: 3.5
Classifier: Programming Language :: Python :: 3.6
Classifier: Programming Language :: Python :: 3.7
Classifier: Programming Language :: Python :: 3.8
Classifier: Framework :: Django
Classifier: Framework :: Django :: 2.2
Classifier: Framework :: Django :: 3.0
Classifier: Framework :: Django :: 3.1
Classifier: Topic :: Software Development
Requires-Python: >=3.5
